garpix_instagram/MANIFEST.in
garpix_instagram/__init__.py
garpix_instagram/apps.py
garpix_instagram/instagram.py
garpix_instagram/setup.py
garpix_instagram/signals.py
garpix_instagram/tests.py
garpix_instagram/views.py
garpix_instagram/__pycache__/__init__.cpython-38.pyc
garpix_instagram/__pycache__/tests.cpython-38.pyc
garpix_instagram/admin/__init__.py
garpix_instagram/admin/inst_hashtag.py
garpix_instagram/admin/instagram_post.py
garpix_instagram/admin/__pycache__/__init__.cpython-38.pyc
garpix_instagram/admin/__pycache__/inst_hashtag.cpython-38.pyc
garpix_instagram/admin/__pycache__/instagram_post.cpython-38.pyc
garpix_instagram/management/commands/start_inst.py
garpix_instagram/migrations/__init__.py
garpix_instagram/migrations/__pycache__/__init__.cpython-38.pyc
garpix_instagram/models/__init__.py
garpix_instagram/models/empty_mixin.py
garpix_instagram/models/inst_hashtag.py
garpix_instagram/models/instagram_post.py
garpix_instagram/models/__pycache__/__init__.cpython-38.pyc
garpix_instagram/models/__pycache__/empty_mixin.cpython-38.pyc
garpix_instagram/models/__pycache__/inst_hashtag.cpython-38.pyc
garpix_instagram/models/__pycache__/instagram_post.cpython-38.pyc
garpix_instagram-1.1.2.dist-info/METADATA
garpix_instagram-1.1.2.dist-info/WHEEL
garpix_instagram-1.1.2.dist-info/top_level.txt
garpix_instagram-1.1.2.dist-info/RECORD
